
{
  "items" : [
  {
    "name" : "worn axe",
    "equippable" : true,
    "kind" : "weapon",
    "stats" : {
      "attack" : 10
    }
  },
  {
    "name" : "rusty knife",
    "equippable" : true,
    "kind" : "weapon",
    "stats" : {
      "attack" : 8
    }
  },
  {
    "name" : "sword of azereon",
    "equippable" : true,
    "kind" : "weapon",
    "stats" : {
      "attack" : 14
    }
  },
  {
    "name" : "apple",
    "equippable" : true,
    "kind" : "food",
    "stats" : {
      "hp" : 20
    }
  }
    ]
}
